{
  "botName": "diana",
  "realizedPnlUsd": 833.3078546917823,
  "costBasis": {
    "BTC": {
      "avgCostUsd": 115549,
      "quantity": "160000000000"
    },
    "ETH": {
      "avgCostUsd": 4467.67,
      "quantity": "160000000000"
    },
    "BNB": {
      "avgCostUsd": 992.32,
      "quantity": "53989842004"
    },
    "XRP": {
      "avgCostUsd": 2.99,
      "quantity": "26848038764"
    },
    "TRX": {
      "avgCostUsd": 0.346768,
      "quantity": "36329511533"
    },
    "DOGE": {
      "avgCostUsd": 0.266636,
      "quantity": "14234140532557"
    },
    "ADA": {
      "avgCostUsd": 0.899353,
      "quantity": "553367691"
    },
    "SOL": {
      "avgCostUsd": 239.21,
      "quantity": "306493850373"
    }
  },
  "lastUpdated": 1758364831126
}